gic/__init__.py
gic/cli.py
gic/compress.py
gic/main.py
gic-4.0.0.dist-info/LICENSE
gic-4.0.0.dist-info/METADATA
gic-4.0.0.dist-info/WHEEL
gic-4.0.0.dist-info/entry_points.txt
gic-4.0.0.dist-info/top_level.txt
gic-4.0.0.dist-info/RECORD
